{
    "cs-en": {
        "cs-en-----./wmt2b_ckpts/cs-envanilla256100__1___finally": {
            "bleu": {
                "1": 0.12376296819780025,
                "2": 0.06981898637107811,
                "3": 0.04291054886191502,
                "4": 0.026689113994880793
            },
            "bertscore": {
                "p": 0.678814172744751,
                "r": 0.7105923295021057,
                "f1": 0.6931983232498169
            },
            "rouge-l": {
                "p": 0.16896449927536036,
                "r": 0.11603236203476693,
                "f1": 0.12918089848734568
            }
        },
        "cs-en-----./wmt2b_ckpts/cs-envanilla256100__2___finally": {
            "bleu": {
                "1": 0.14251134644478064,
                "2": 0.08539503655000816,
                "3": 0.05603188928673651,
                "4": 0.037802596584712723
            },
            "bertscore": {
                "p": 0.8189272880554199,
                "r": 0.8608668446540833,
                "f1": 0.8384596109390259
            },
            "rouge-l": {
                "p": 0.28398321774843505,
                "r": 0.2323346092100013,
                "f1": 0.24262030142312002
            }
        },
        "cs-en-----./wmt2b_ckpts/cs-envanilla256100__3___finally": {
            "bleu": {
                "1": 0.10271132376395532,
                "2": 0.05843539249042514,
                "3": 0.03501899370330739,
                "4": 0.021032366538963003
            },
            "bertscore": {
                "p": 0.7748333215713501,
                "r": 0.8234847187995911,
                "f1": 0.797197699546814
            },
            "rouge-l": {
                "p": 0.24954433360987444,
                "r": 0.1665757929778928,
                "f1": 0.18340701163268666
            }
        },
        "cs-en-----./wmt2b_ckpts/cs-envanilla256100__4___finally": {
            "bleu": {
                "1": 0.12858312858312862,
                "2": 0.06943473550614562,
                "3": 0.04436294156100797,
                "4": 0.029906067987869343
            },
            "bertscore": {
                "p": 0.7596719264984131,
                "r": 0.8067582845687866,
                "f1": 0.7814720273017883
            },
            "rouge-l": {
                "p": 0.1897513115396747,
                "r": 0.14111228888046698,
                "f1": 0.15409010287811012
            }
        },
        "cs-en-----./wmt2b_ckpts/cs-envanilla256100__5___finally": {
            "bleu": {
                "1": 0.06802218114602589,
                "2": 0.0363050820295588,
                "3": 0.021755795022838767,
                "4": 0.013486643532169575
            },
            "bertscore": {
                "p": 0.572091817855835,
                "r": 0.609112560749054,
                "f1": 0.5890371203422546
            },
            "rouge-l": {
                "p": 0.170615224630442,
                "r": 0.08560282496003845,
                "f1": 0.10366116761700667
            }
        },
        "cs-en-----./wmt2b_ckpts/cs-enkd256100__1___finally": {
            "bleu": {
                "1": 0.17222861526658995,
                "2": 0.09117340471686627,
                "3": 0.05375647619929054,
                "4": 0.03057116400987978
            },
            "bertscore": {
                "p": 0.8380943536758423,
                "r": 0.8606801629066467,
                "f1": 0.8480852246284485
            },
            "rouge-l": {
                "p": 0.29252429104201194,
                "r": 0.22923801856743903,
                "f1": 0.2441815236414354
            }
        },
        "cs-en-----./wmt2b_ckpts/cs-enkd256100__2___finally": {
            "bleu": {
                "1": 0.1152181152181152,
                "2": 0.06008731160106677,
                "3": 0.03378805813245799,
                "4": 0.019418244991824422
            },
            "bertscore": {
                "p": 0.7811315655708313,
                "r": 0.8375056982040405,
                "f1": 0.807029128074646
            },
            "rouge-l": {
                "p": 0.2401380914481937,
                "r": 0.17821251881771935,
                "f1": 0.19554100738409108
            }
        },
        "cs-en-----./wmt2b_ckpts/cs-enkd256100__3___finally": {
            "bleu": {
                "1": 0.20132325141776938,
                "2": 0.10944215644532614,
                "3": 0.06500034500551223,
                "4": 0.039402164048319435
            },
            "bertscore": {
                "p": 0.8381599187850952,
                "r": 0.8566223382949829,
                "f1": 0.8462796807289124
            },
            "rouge-l": {
                "p": 0.2603495346408765,
                "r": 0.23115710991282273,
                "f1": 0.23650126599747787
            }
        },
        "cs-en-----./wmt2b_ckpts/cs-enkd256100__4___finally": {
            "bleu": {
                "1": 0.11492122335495827,
                "2": 0.06541690014912796,
                "3": 0.04231470141050459,
                "4": 0.028832777048749893
            },
            "bertscore": {
                "p": 0.7679688334465027,
                "r": 0.8157561421394348,
                "f1": 0.7893453240394592
            },
            "rouge-l": {
                "p": 0.25152774704655495,
                "r": 0.20132204259841022,
                "f1": 0.21126837980346427
            }
        },
        "cs-en-----./wmt2b_ckpts/cs-enkd256100__5___finally": {
            "bleu": {
                "1": 0.10995128740431455,
                "2": 0.047946943570816615,
                "3": 0.022911556501278775,
                "4": 0.011684467965881955
            },
            "bertscore": {
                "p": 0.7931376099586487,
                "r": 0.8473634123802185,
                "f1": 0.8178317546844482
            },
            "rouge-l": {
                "p": 0.23666107832655814,
                "r": 0.16909230595209673,
                "f1": 0.18568167030388175
            }
        }
    },
    "de-en": {
        "de-en-----./wmt2b_ckpts/de-envanilla256100__1___finally": {
            "bleu": {
                "1": 0.35305583869769774,
                "2": 0.25054351264500563,
                "3": 0.18310339907246023,
                "4": 0.1397053168331808
            },
            "bertscore": {
                "p": 0.8796956539154053,
                "r": 0.8958317637443542,
                "f1": 0.8871656656265259
            },
            "rouge-l": {
                "p": 0.3574157717903052,
                "r": 0.34367045730368423,
                "f1": 0.3450699754986801
            }
        },
        "de-en-----./wmt2b_ckpts/de-envanilla256100__2___finally": {
            "bleu": {
                "1": 0.1967935871743487,
                "2": 0.12781975838329743,
                "3": 0.08764952227705744,
                "4": 0.06276381817112484
            },
            "bertscore": {
                "p": 0.8083049654960632,
                "r": 0.8473401665687561,
                "f1": 0.8263220191001892
            },
            "rouge-l": {
                "p": 0.3079186340243548,
                "r": 0.2283702730073971,
                "f1": 0.2531105753113829
            }
        },
        "de-en-----./wmt2b_ckpts/de-envanilla256100__3___finally": {
            "bleu": {
                "1": 0.2635498551923873,
                "2": 0.15079594838518143,
                "3": 0.09159978107708279,
                "4": 0.059683443550159025
            },
            "bertscore": {
                "p": 0.8366909623146057,
                "r": 0.8658499121665955,
                "f1": 0.8506126999855042
            },
            "rouge-l": {
                "p": 0.3781191762371585,
                "r": 0.32520910603178704,
                "f1": 0.3390322817424527
            }
        },
        "de-en-----./wmt2b_ckpts/de-envanilla256100__4___finally": {
            "bleu": {
                "1": 0.2365626204977368,
                "2": 0.13956398936214567,
                "3": 0.08564638347845813,
                "4": 0.05510897004254139
            },
            "bertscore": {
                "p": 0.8182342648506165,
                "r": 0.8352198600769043,
                "f1": 0.8259420990943909
            },
            "rouge-l": {
                "p": 0.30959758214577277,
                "r": 0.2398255547584843,
                "f1": 0.2596090121980669
            }
        },
        "de-en-----./wmt2b_ckpts/de-envanilla256100__5___finally": {
            "bleu": {
                "1": 0.18446244477172313,
                "2": 0.10899721894251803,
                "3": 0.06764668618697321,
                "4": 0.044523459665683184
            },
            "bertscore": {
                "p": 0.7582604885101318,
                "r": 0.7942338585853577,
                "f1": 0.7750243544578552
            },
            "rouge-l": {
                "p": 0.25521908086072576,
                "r": 0.22369101234202365,
                "f1": 0.22504358391021742
            }
        },
        "de-en-----./wmt2b_ckpts/de-enkd256100__1___finally": {
            "bleu": {
                "1": 0.41988417095021546,
                "2": 0.2772121449967495,
                "3": 0.18768504532935512,
                "4": 0.13088731684129049
            },
            "bertscore": {
                "p": 0.8840755224227905,
                "r": 0.9049001932144165,
                "f1": 0.8941226005554199
            },
            "rouge-l": {
                "p": 0.4339199628924972,
                "r": 0.4042984569642437,
                "f1": 0.4135317857899836
            }
        },
        "de-en-----./wmt2b_ckpts/de-enkd256100__2___finally": {
            "bleu": {
                "1": 0.10208502572434335,
                "2": 0.05666196538119931,
                "3": 0.033251779467274235,
                "4": 0.01973545814249692
            },
            "bertscore": {
                "p": 0.7557138800621033,
                "r": 0.846052885055542,
                "f1": 0.7964314222335815
            },
            "rouge-l": {
                "p": 0.3235986382481032,
                "r": 0.2027281316182719,
                "f1": 0.23502314132993343
            }
        },
        "de-en-----./wmt2b_ckpts/de-enkd256100__3___finally": {
            "bleu": {
                "1": 0.06071179344033495,
                "2": 0.03577440505291534,
                "3": 0.02167753156795402,
                "4": 0.01495774989157572
            },
            "bertscore": {
                "p": 0.5265241265296936,
                "r": 0.6407434344291687,
                "f1": 0.576704740524292
            },
            "rouge-l": {
                "p": 0.16615156455932317,
                "r": 0.12428384746417363,
                "f1": 0.1316889550099798
            }
        },
        "de-en-----./wmt2b_ckpts/de-enkd256100__4___finally": {
            "bleu": {
                "1": 0.21903052064631956,
                "2": 0.12868507846460833,
                "3": 0.078322348219652,
                "4": 0.05063518555705165
            },
            "bertscore": {
                "p": 0.8212347626686096,
                "r": 0.8693052530288696,
                "f1": 0.8436575531959534
            },
            "rouge-l": {
                "p": 0.34684995764899773,
                "r": 0.2946657169203218,
                "f1": 0.30927011947753796
            }
        },
        "de-en-----./wmt2b_ckpts/de-enkd256100__5___finally": {
            "bleu": {
                "1": 0.005734709469569216,
                "2": 0.0029518248097184356,
                "3": 0.0015794944307480998,
                "4": 0.0
            },
            "bertscore": {
                "p": 0.16732025146484375,
                "r": 0.17019149661064148,
                "f1": 0.16858191788196564
            },
            "rouge-l": {
                "p": 0.05446148459383754,
                "r": 0.039512446595920146,
                "f1": 0.04506356993392014
            }
        }
    },
    "fi-en": {
        "fi-en-----./wmt2b_ckpts/fi-envanilla256100__1___finally": {
            "bleu": {
                "1": 0.11385516952699874,
                "2": 0.059648755625903147,
                "3": 0.03635731676684721,
                "4": 0.02177164137179683
            },
            "bertscore": {
                "p": 0.6668788194656372,
                "r": 0.7194166779518127,
                "f1": 0.6909840106964111
            },
            "rouge-l": {
                "p": 0.24557370012168764,
                "r": 0.1505336702411687,
                "f1": 0.17497428148908434
            }
        },
        "fi-en-----./wmt2b_ckpts/fi-envanilla256100__2___finally": {
            "bleu": {
                "1": 0.13630880579010857,
                "2": 0.07195139951867585,
                "3": 0.041564920908555375,
                "4": 0.0238509616045025
            },
            "bertscore": {
                "p": 0.7264045476913452,
                "r": 0.7742335796356201,
                "f1": 0.7488512992858887
            },
            "rouge-l": {
                "p": 0.2537700777891504,
                "r": 0.17384506777346206,
                "f1": 0.19583358477074203
            }
        },
        "fi-en-----./wmt2b_ckpts/fi-envanilla256100__3___finally": {
            "bleu": {
                "1": 0.14277158590566502,
                "2": 0.0830864332663585,
                "3": 0.052671506316257465,
                "4": 0.03486945085843544
            },
            "bertscore": {
                "p": 0.7301640510559082,
                "r": 0.7669396996498108,
                "f1": 0.7472683191299438
            },
            "rouge-l": {
                "p": 0.19476170693799655,
                "r": 0.15665328083750638,
                "f1": 0.1682664267811959
            }
        },
        "fi-en-----./wmt2b_ckpts/fi-envanilla256100__4___finally": {
            "bleu": {
                "1": 0.09216585309269534,
                "2": 0.03858712662176157,
                "3": 0.02254043148208148,
                "4": 0.015145691326283973
            },
            "bertscore": {
                "p": 0.8131986260414124,
                "r": 0.8236526250839233,
                "f1": 0.8179112076759338
            },
            "rouge-l": {
                "p": 0.15127462887989193,
                "r": 0.09484693189007437,
                "f1": 0.1109809459708071
            }
        },
        "fi-en-----./wmt2b_ckpts/fi-envanilla256100__5___finally": {
            "bleu": {
                "1": 0.13123092573753814,
                "2": 0.06441518854910791,
                "3": 0.035440828689414144,
                "4": 0.019974123214704022
            },
            "bertscore": {
                "p": 0.7984695434570312,
                "r": 0.8460636138916016,
                "f1": 0.8203095197677612
            },
            "rouge-l": {
                "p": 0.2715218166252541,
                "r": 0.1540883640374023,
                "f1": 0.17973884853698874
            }
        },
        "fi-en-----./wmt2b_ckpts/fi-enkd256100__1___finally": {
            "bleu": {
                "1": 0.1320998278829604,
                "2": 0.06584839054620263,
                "3": 0.03804494357368509,
                "4": 0.020874842563932714
            },
            "bertscore": {
                "p": 0.7797638177871704,
                "r": 0.8471695780754089,
                "f1": 0.8110268115997314
            },
            "rouge-l": {
                "p": 0.22371913424691306,
                "r": 0.16555689427497755,
                "f1": 0.18193453832552198
            }
        },
        "fi-en-----./wmt2b_ckpts/fi-enkd256100__2___finally": {
            "bleu": {
                "1": 0.0708382526564345,
                "2": 0.03314767740704002,
                "3": 0.018347875938579207,
                "4": 0.008781532189844194
            },
            "bertscore": {
                "p": 0.7708393931388855,
                "r": 0.8349826335906982,
                "f1": 0.8003450036048889
            },
            "rouge-l": {
                "p": 0.19254415999862895,
                "r": 0.11878623505082882,
                "f1": 0.13754276608591312
            }
        },
        "fi-en-----./wmt2b_ckpts/fi-enkd256100__3___finally": {
            "bleu": {
                "1": 0.11421911421911421,
                "2": 0.05680058416068106,
                "3": 0.031017446055226935,
                "4": 0.017726497266684717
            },
            "bertscore": {
                "p": 0.7746176719665527,
                "r": 0.8431826233863831,
                "f1": 0.8064016103744507
            },
            "rouge-l": {
                "p": 0.2322247574027876,
                "r": 0.1767897237740349,
                "f1": 0.1893013586971903
            }
        },
        "fi-en-----./wmt2b_ckpts/fi-enkd256100__4___finally": {
            "bleu": {
                "1": 0.07890070921985815,
                "2": 0.034659626747071556,
                "3": 0.017411786864213307,
                "4": 0.009093439499416314
            },
            "bertscore": {
                "p": 0.7468106150627136,
                "r": 0.8380988836288452,
                "f1": 0.7884676456451416
            },
            "rouge-l": {
                "p": 0.20241996629961018,
                "r": 0.13163046110774088,
                "f1": 0.15109120956244076
            }
        },
        "fi-en-----./wmt2b_ckpts/fi-enkd256100__5___finally": {
            "bleu": {
                "1": 0.14635931211123307,
                "2": 0.07855000909439983,
                "3": 0.047138444611666885,
                "4": 0.02966976013769753
            },
            "bertscore": {
                "p": 0.8212016224861145,
                "r": 0.8572683930397034,
                "f1": 0.8381791114807129
            },
            "rouge-l": {
                "p": 0.249106395075326,
                "r": 0.20482701996923436,
                "f1": 0.21752910316371998
            }
        }
    },
    "ro-en": {
        "ro-en-----./wmt2b_ckpts/ro-envanilla256100__1___finally": {
            "bleu": {
                "1": 0.24168421052631578,
                "2": 0.13279676109410582,
                "3": 0.07297701732356228,
                "4": 0.04157684758931776
            },
            "bertscore": {
                "p": 0.8264076113700867,
                "r": 0.8742234110832214,
                "f1": 0.8488742709159851
            },
            "rouge-l": {
                "p": 0.2876486795754383,
                "r": 0.24462491045965376,
                "f1": 0.256778429190071
            }
        },
        "ro-en-----./wmt2b_ckpts/ro-envanilla256100__2___finally": {
            "bleu": {
                "1": 0.29080756013745707,
                "2": 0.17250936501956213,
                "3": 0.11069852171515915,
                "4": 0.07406089953713506
            },
            "bertscore": {
                "p": 0.8551494479179382,
                "r": 0.8780738711357117,
                "f1": 0.8659090995788574
            },
            "rouge-l": {
                "p": 0.322072082682895,
                "r": 0.27865933531707043,
                "f1": 0.2885072098286308
            }
        },
        "ro-en-----./wmt2b_ckpts/ro-envanilla256100__3___finally": {
            "bleu": {
                "1": 0.1444947209653092,
                "2": 0.08238041498545794,
                "3": 0.04867985057627139,
                "4": 0.0295496400728079
            },
            "bertscore": {
                "p": 0.789693295955658,
                "r": 0.854326605796814,
                "f1": 0.8193141222000122
            },
            "rouge-l": {
                "p": 0.2732868101388915,
                "r": 0.18220517958284077,
                "f1": 0.20370769927697674
            }
        },
        "ro-en-----./wmt2b_ckpts/ro-envanilla256100__4___finally": {
            "bleu": {
                "1": 0.2092365692742696,
                "2": 0.11987288048121385,
                "3": 0.07186247622960018,
                "4": 0.04628394368012809
            },
            "bertscore": {
                "p": 0.8043174743652344,
                "r": 0.8450353741645813,
                "f1": 0.8231155276298523
            },
            "rouge-l": {
                "p": 0.20457273762024897,
                "r": 0.17902624029522282,
                "f1": 0.18487117987945856
            }
        },
        "ro-en-----./wmt2b_ckpts/ro-envanilla256100__5___finally": {
            "bleu": {
                "1": 0.3114610673665792,
                "2": 0.18771866168001025,
                "3": 0.12193884352511294,
                "4": 0.0827886015555984
            },
            "bertscore": {
                "p": 0.8158328533172607,
                "r": 0.8332008123397827,
                "f1": 0.8237934708595276
            },
            "rouge-l": {
                "p": 0.344009050351361,
                "r": 0.29642965263409293,
                "f1": 0.30845160486647477
            }
        },
        "ro-en-----./wmt2b_ckpts/ro-enkd256100__1___finally": {
            "bleu": {
                "1": 0.20448498669707335,
                "2": 0.11684980541534785,
                "3": 0.07064296246031593,
                "4": 0.04444040917573817
            },
            "bertscore": {
                "p": 0.8281451463699341,
                "r": 0.8628568053245544,
                "f1": 0.8440725207328796
            },
            "rouge-l": {
                "p": 0.28300715728229864,
                "r": 0.2223869510866363,
                "f1": 0.23606660421394793
            }
        },
        "ro-en-----./wmt2b_ckpts/ro-enkd256100__2___finally": {
            "bleu": {
                "1": 0.2774869109947644,
                "2": 0.15600279272426484,
                "3": 0.09274489128186039,
                "4": 0.0564933524101897
            },
            "bertscore": {
                "p": 0.8536753058433533,
                "r": 0.8755796551704407,
                "f1": 0.8640249371528625
            },
            "rouge-l": {
                "p": 0.297404525610476,
                "r": 0.2905921928853138,
                "f1": 0.2873848419173782
            }
        },
        "ro-en-----./wmt2b_ckpts/ro-enkd256100__3___finally": {
            "bleu": {
                "1": 0.11540941328175372,
                "2": 0.062302236544717234,
                "3": 0.037012553660966334,
                "4": 0.022798958208403504
            },
            "bertscore": {
                "p": 0.7590910196304321,
                "r": 0.834296703338623,
                "f1": 0.792693018913269
            },
            "rouge-l": {
                "p": 0.21752552867770583,
                "r": 0.13875558510415403,
                "f1": 0.15602783304269152
            }
        },
        "ro-en-----./wmt2b_ckpts/ro-enkd256100__4___finally": {
            "bleu": {
                "1": 0.2395264116575592,
                "2": 0.13551269888985637,
                "3": 0.0800469053533415,
                "4": 0.04930100112588153
            },
            "bertscore": {
                "p": 0.8051424622535706,
                "r": 0.8378996849060059,
                "f1": 0.8204307556152344
            },
            "rouge-l": {
                "p": 0.30273870498558736,
                "r": 0.2419314772185322,
                "f1": 0.25595815477772754
            }
        },
        "ro-en-----./wmt2b_ckpts/ro-enkd256100__5___finally": {
            "bleu": {
                "1": 0.2676786375416512,
                "2": 0.15683234309852728,
                "3": 0.09268788915690307,
                "4": 0.05565995329409961
            },
            "bertscore": {
                "p": 0.847798228263855,
                "r": 0.8764945864677429,
                "f1": 0.8609108924865723
            },
            "rouge-l": {
                "p": 0.36355856866859,
                "r": 0.29806980625949825,
                "f1": 0.31675510252067945
            }
        }
    },
    "ru-en": {
        "ru-en-----./wmt2b_ckpts/ru-envanilla256100__1___finally": {
            "bleu": {
                "1": 0.14582623509369677,
                "2": 0.08725135049740812,
                "3": 0.05713303071632138,
                "4": 0.0396722930298989
            },
            "bertscore": {
                "p": 0.841183066368103,
                "r": 0.8577908277511597,
                "f1": 0.8487308025360107
            },
            "rouge-l": {
                "p": 0.29906405749318654,
                "r": 0.18180134097426293,
                "f1": 0.21562072414268582
            }
        },
        "ru-en-----./wmt2b_ckpts/ru-envanilla256100__2___finally": {
            "bleu": {
                "1": 0.09726469804647728,
                "2": 0.04651290599972682,
                "3": 0.026740432169455704,
                "4": 0.015124290930230155
            },
            "bertscore": {
                "p": 0.6918419003486633,
                "r": 0.7983017563819885,
                "f1": 0.7393232583999634
            },
            "rouge-l": {
                "p": 0.11227527956195006,
                "r": 0.0720696988512004,
                "f1": 0.08124008682758489
            }
        },
        "ru-en-----./wmt2b_ckpts/ru-envanilla256100__3___finally": {
            "bleu": {
                "1": 0.0832642007008043,
                "2": 0.03741684057513768,
                "3": 0.02050619098386825,
                "4": 0.012983546252859815
            },
            "bertscore": {
                "p": 0.8136892914772034,
                "r": 0.8329800367355347,
                "f1": 0.8220931887626648
            },
            "rouge-l": {
                "p": 0.16496116787409354,
                "r": 0.07917943358522785,
                "f1": 0.10156205696736792
            }
        },
        "ru-en-----./wmt2b_ckpts/ru-envanilla256100__4___finally": {
            "bleu": {
                "1": 0.16339227242960053,
                "2": 0.09894574985841367,
                "3": 0.061836425873544154,
                "4": 0.041902728999876356
            },
            "bertscore": {
                "p": 0.8166738152503967,
                "r": 0.8597387671470642,
                "f1": 0.836219847202301
            },
            "rouge-l": {
                "p": 0.277212291925071,
                "r": 0.20874292909740652,
                "f1": 0.2261119089875534
            }
        },
        "ru-en-----./wmt2b_ckpts/ru-envanilla256100__5___finally": {
            "bleu": {
                "1": 0.17566594672426206,
                "2": 0.10497675522369229,
                "3": 0.06873577703689306,
                "4": 0.0459350236173479
            },
            "bertscore": {
                "p": 0.8173794746398926,
                "r": 0.8573918342590332,
                "f1": 0.8355742692947388
            },
            "rouge-l": {
                "p": 0.27810614018334606,
                "r": 0.19038740149889521,
                "f1": 0.21338292495782285
            }
        },
        "ru-en-----./wmt2b_ckpts/ru-enkd256100__1___finally": {
            "bleu": {
                "1": 0.080354500017178,
                "2": 0.042141062455011646,
                "3": 0.024144509346517296,
                "4": 0.015264059808823583
            },
            "bertscore": {
                "p": 0.535624086856842,
                "r": 0.5566533803939819,
                "f1": 0.5447308421134949
            },
            "rouge-l": {
                "p": 0.12769640301219248,
                "r": 0.06930957771099758,
                "f1": 0.08682410805923121
            }
        },
        "ru-en-----./wmt2b_ckpts/ru-enkd256100__2___finally": {
            "bleu": {
                "1": 0.1334778569216476,
                "2": 0.0691211320547074,
                "3": 0.03732519991754707,
                "4": 0.02190712662824982
            },
            "bertscore": {
                "p": 0.8093029260635376,
                "r": 0.8506878614425659,
                "f1": 0.8285537958145142
            },
            "rouge-l": {
                "p": 0.25873427122804393,
                "r": 0.1875485304915471,
                "f1": 0.20401514952805147
            }
        },
        "ru-en-----./wmt2b_ckpts/ru-enkd256100__3___finally": {
            "bleu": {
                "1": 0.16252189141856394,
                "2": 0.09248666800610661,
                "3": 0.05930215735470175,
                "4": 0.03912888229917682
            },
            "bertscore": {
                "p": 0.8007870316505432,
                "r": 0.8532806634902954,
                "f1": 0.8248470425605774
            },
            "rouge-l": {
                "p": 0.2668649288758597,
                "r": 0.1952225073699729,
                "f1": 0.21513003621798799
            }
        },
        "ru-en-----./wmt2b_ckpts/ru-enkd256100__4___finally": {
            "bleu": {
                "1": 0.08027972027972027,
                "2": 0.032242727862653836,
                "3": 0.013492389280118339,
                "4": 0.006212900655670171
            },
            "bertscore": {
                "p": 0.7603182792663574,
                "r": 0.8297451734542847,
                "f1": 0.7923187017440796
            },
            "rouge-l": {
                "p": 0.2098620429749461,
                "r": 0.09691588637481396,
                "f1": 0.12567541802088542
            }
        },
        "ru-en-----./wmt2b_ckpts/ru-enkd256100__5___finally": {
            "bleu": {
                "1": 0.24192921042395957,
                "2": 0.14441010476093175,
                "3": 0.09213595566223488,
                "4": 0.06164371884582191
            },
            "bertscore": {
                "p": 0.8427674770355225,
                "r": 0.8705695271492004,
                "f1": 0.8553493022918701
            },
            "rouge-l": {
                "p": 0.290583652120224,
                "r": 0.24821278501346009,
                "f1": 0.25768329898808057
            }
        }
    },
    "tr-en": {
        "tr-en-----./wmt2b_ckpts/tr-envanilla256100__1___finally": {
            "bleu": {
                "1": 0.1122448979591837,
                "2": 0.05464041119370245,
                "3": 0.02904417036751327,
                "4": 0.016509410600040183
            },
            "bertscore": {
                "p": 0.7606629729270935,
                "r": 0.7889862656593323,
                "f1": 0.7732696533203125
            },
            "rouge-l": {
                "p": 0.15359581768654534,
                "r": 0.08878631102064549,
                "f1": 0.10593684468992412
            }
        },
        "tr-en-----./wmt2b_ckpts/tr-envanilla256100__2___finally": {
            "bleu": {
                "1": 0.06500525578529096,
                "2": 0.027530723511374453,
                "3": 0.012854784135415898,
                "4": 0.005955089415149634
            },
            "bertscore": {
                "p": 0.7251120209693909,
                "r": 0.7435468435287476,
                "f1": 0.7329604625701904
            },
            "rouge-l": {
                "p": 0.08959195308077483,
                "r": 0.05889052650921095,
                "f1": 0.06843938824081651
            }
        },
        "tr-en-----./wmt2b_ckpts/tr-envanilla256100__3___finally": {
            "bleu": {
                "1": 0.15087719298245614,
                "2": 0.0695985056249502,
                "3": 0.03176249411932371,
                "4": 0.013873368479261168
            },
            "bertscore": {
                "p": 0.7707865238189697,
                "r": 0.8098822832107544,
                "f1": 0.7887676954269409
            },
            "rouge-l": {
                "p": 0.21573740545062375,
                "r": 0.14924094124577172,
                "f1": 0.17080447832050866
            }
        },
        "tr-en-----./wmt2b_ckpts/tr-envanilla256100__4___finally": {
            "bleu": {
                "1": 0.04237252128025889,
                "2": 0.019789102410717452,
                "3": 0.011548562200600907,
                "4": 0.0071942988254778744
            },
            "bertscore": {
                "p": 0.36055588722229004,
                "r": 0.3787357807159424,
                "f1": 0.36878708004951477
            },
            "rouge-l": {
                "p": 0.09597054508672155,
                "r": 0.04219401836174207,
                "f1": 0.05356210461435168
            }
        },
        "tr-en-----./wmt2b_ckpts/tr-envanilla256100__5___finally": {
            "bleu": {
                "1": 0.05564279855279012,
                "2": 0.025020844400541836,
                "3": 0.01525881504073971,
                "4": 0.009919636320356473
            },
            "bertscore": {
                "p": 0.3974039554595947,
                "r": 0.4354996085166931,
                "f1": 0.41495829820632935
            },
            "rouge-l": {
                "p": 0.10864952939217642,
                "r": 0.054211590653056516,
                "f1": 0.0688969871324395
            }
        },
        "tr-en-----./wmt2b_ckpts/tr-enkd256100__1___finally": {
            "bleu": {
                "1": 0.10625213529210797,
                "2": 0.0466730687180937,
                "3": 0.02286903077458552,
                "4": 0.0116057519614388
            },
            "bertscore": {
                "p": 0.7629645466804504,
                "r": 0.8305405974388123,
                "f1": 0.7938003540039062
            },
            "rouge-l": {
                "p": 0.21905281608320032,
                "r": 0.1426069287685122,
                "f1": 0.1667137273346708
            }
        },
        "tr-en-----./wmt2b_ckpts/tr-enkd256100__2___finally": {
            "bleu": {
                "1": 0.14026548672566372,
                "2": 0.06292351074644352,
                "3": 0.03316093403659674,
                "4": 0.01962417792556617
            },
            "bertscore": {
                "p": 0.7786127328872681,
                "r": 0.8415161371231079,
                "f1": 0.8077983260154724
            },
            "rouge-l": {
                "p": 0.2063667564740931,
                "r": 0.15190472287955148,
                "f1": 0.16925907553287506
            }
        },
        "tr-en-----./wmt2b_ckpts/tr-enkd256100__3___finally": {
            "bleu": {
                "1": 0.13572854291417166,
                "2": 0.061030934633675836,
                "3": 0.02894055066191523,
                "4": 0.016651525219305713
            },
            "bertscore": {
                "p": 0.7948625087738037,
                "r": 0.8531728982925415,
                "f1": 0.8221264481544495
            },
            "rouge-l": {
                "p": 0.2036306199371887,
                "r": 0.17157168993749822,
                "f1": 0.18042453033107464
            }
        },
        "tr-en-----./wmt2b_ckpts/tr-enkd256100__4___finally": {
            "bleu": {
                "1": 0.16228287841191066,
                "2": 0.07248494382796555,
                "3": 0.03351100444835274,
                "4": 0.018199818379197805
            },
            "bertscore": {
                "p": 0.8058551549911499,
                "r": 0.8562988042831421,
                "f1": 0.8298752307891846
            },
            "rouge-l": {
                "p": 0.20651516187963295,
                "r": 0.16631695983508343,
                "f1": 0.1799158447104596
            }
        },
        "tr-en-----./wmt2b_ckpts/tr-enkd256100__5___finally": {
            "bleu": {
                "1": 0.11099656357388314,
                "2": 0.04866567300646803,
                "3": 0.02502551495554522,
                "4": 0.015219495198091288
            },
            "bertscore": {
                "p": 0.7524334788322449,
                "r": 0.827983021736145,
                "f1": 0.7869085669517517
            },
            "rouge-l": {
                "p": 0.21827623703266108,
                "r": 0.15232026037558782,
                "f1": 0.1728714780447082
            }
        }
    }
}