{
    "cs-en": {
        "cs-en-----./wmt2b_ckpts/cs-enComplex-lord256100___period2": {
            "bleu": {
                "1": 0.16329704510108864,
                "2": 0.06943511997527438,
                "3": 0.03385158873480783,
                "4": 0.01851356370126601
            },
            "bertscore": {
                "p": 0.8379013538360596,
                "r": 0.8427464365959167,
                "f1": 0.840080738067627
            },
            "rouge-l": {
                "p": 0.14926574786511568,
                "r": 0.15725238103447103,
                "f1": 0.14579891657662342
            }
        },
        "cs-en-----./wmt2b_ckpts/cs-envanilla256100___finally": {
            "bleu": {
                "1": 0.09504770956780467,
                "2": 0.05575626696242794,
                "3": 0.03387609353961929,
                "4": 0.020657480246917836
            },
            "bertscore": {
                "p": 0.34203165769577026,
                "r": 0.35225722193717957,
                "f1": 0.3468264043331146
            },
            "rouge-l": {
                "p": 0.12408681295855209,
                "r": 0.07208582713900087,
                "f1": 0.08171512941996883
            }
        },
        "cs-en-----./wmt2b_ckpts/cs-enkd256100___finally": {
            "bleu": {
                "1": 0.0005319148936170212,
                "2": 0.0,
                "3": 0.0,
                "4": 0.0
            },
            "bertscore": {
                "p": 0.6495435237884521,
                "r": 0.8098940253257751,
                "f1": 0.7205044031143188
            },
            "rouge-l": {
                "p": 0.009166666666666667,
                "r": 0.0031475485661424606,
                "f1": 0.00366923068753657
            }
        },
        "cs-en-----./wmt2b_ckpts/cs-enblack--Complex-lord256100___period2": {
            "bleu": {
                "1": 0.1145930776426567,
                "2": 0.04241818589802954,
                "3": 0.020992372566380917,
                "4": 0.011887548097502821
            },
            "bertscore": {
                "p": 0.7670155167579651,
                "r": 0.8339969515800476,
                "f1": 0.7977359890937805
            },
            "rouge-l": {
                "p": 0.16048183468578203,
                "r": 0.10392561771205477,
                "f1": 0.11617081203886652
            }
        }
    },
    "de-en": {
        "de-en-----./wmt2b_ckpts/de-enComplex-lord256100___period2": {
            "bleu": {
                "1": 0.26768128916741274,
                "2": 0.1523342870229752,
                "3": 0.09492138348304968,
                "4": 0.06223781404216984
            },
            "bertscore": {
                "p": 0.8469952344894409,
                "r": 0.8705066442489624,
                "f1": 0.8579836487770081
            },
            "rouge-l": {
                "p": 0.33065420645723714,
                "r": 0.29795441069989415,
                "f1": 0.30507305267845203
            }
        },
        "de-en-----./wmt2b_ckpts/de-envanilla256100___finally": {
            "bleu": {
                "1": 0.24282907662082515,
                "2": 0.15753353687698363,
                "3": 0.1060652487736413,
                "4": 0.07572615691605925
            },
            "bertscore": {
                "p": 0.7755786776542664,
                "r": 0.790336012840271,
                "f1": 0.7825271487236023
            },
            "rouge-l": {
                "p": 0.3664928105215558,
                "r": 0.32595635780981275,
                "f1": 0.3349743140741072
            }
        },
        "de-en-----./wmt2b_ckpts/de-enkd256100___finally": {
            "bleu": {
                "1": 0.27465362673186633,
                "2": 0.17267948762582258,
                "3": 0.11282564255624543,
                "4": 0.07972112751814558
            },
            "bertscore": {
                "p": 0.8228241205215454,
                "r": 0.845855176448822,
                "f1": 0.8334782123565674
            },
            "rouge-l": {
                "p": 0.3597996739782628,
                "r": 0.3156997173685877,
                "f1": 0.32956942933211303
            }
        },
        "de-en-----./wmt2b_ckpts/de-enblack--Complex-lord256100___period2": {
            "bleu": {
                "1": 0.1742707554225879,
                "2": 0.09199473910632852,
                "3": 0.05062939754283958,
                "4": 0.030060646858281304
            },
            "bertscore": {
                "p": 0.8088581562042236,
                "r": 0.8544769287109375,
                "f1": 0.8302183747291565
            },
            "rouge-l": {
                "p": 0.2679005598539535,
                "r": 0.21506329848302086,
                "f1": 0.22815859496476357
            }
        }
    },
    "fi-en": {
        "fi-en-----./wmt2b_ckpts/fi-enComplex-lord256100___period2": {
            "bleu": {
                "1": 0.15050924179554884,
                "2": 0.06607576722264671,
                "3": 0.03496163504214643,
                "4": 0.018880639350161717
            },
            "bertscore": {
                "p": 0.8315380215644836,
                "r": 0.8467288017272949,
                "f1": 0.838538408279419
            },
            "rouge-l": {
                "p": 0.18262549478310383,
                "r": 0.1871420192252681,
                "f1": 0.17898083074707322
            }
        },
        "fi-en-----./wmt2b_ckpts/fi-envanilla256100___finally": {
            "bleu": {
                "1": 0.06286347272223762,
                "2": 0.03301537118562052,
                "3": 0.01968988450238493,
                "4": 0.012296408195817357
            },
            "bertscore": {
                "p": 0.6970669627189636,
                "r": 0.7756720781326294,
                "f1": 0.7326477766036987
            },
            "rouge-l": {
                "p": 0.2809670142375385,
                "r": 0.13534671152769376,
                "f1": 0.15372050140539054
            }
        },
        "fi-en-----./wmt2b_ckpts/fi-enkd256100___finally": {
            "bleu": {
                "1": 0.006926546391752576,
                "2": 0.0035318740030413393,
                "3": 0.0018399269397107725,
                "4": 0.0
            },
            "bertscore": {
                "p": 0.6614599823951721,
                "r": 0.8104187250137329,
                "f1": 0.7279057502746582
            },
            "rouge-l": {
                "p": 0.09103571428571426,
                "r": 0.030511678471873322,
                "f1": 0.04190300684555171
            }
        },
        "fi-en-----./wmt2b_ckpts/fi-enblack--Complex-lord256100___period2": {
            "bleu": {
                "1": 0.16745182012847964,
                "2": 0.07293489244881311,
                "3": 0.03617502210020053,
                "4": 0.018465227447979942
            },
            "bertscore": {
                "p": 0.8411307334899902,
                "r": 0.8526004552841187,
                "f1": 0.8464353680610657
            },
            "rouge-l": {
                "p": 0.19971420259091502,
                "r": 0.19090964753707695,
                "f1": 0.1911361183634247
            }
        }
    },
    "ro-en": {
        "ro-en-----./wmt2b_ckpts/ro-enComplex-lord256100___period2": {
            "bleu": {
                "1": 0.19524405506883608,
                "2": 0.08843054988740201,
                "3": 0.042111389560800204,
                "4": 0.024411241149534114
            },
            "bertscore": {
                "p": 0.8312535881996155,
                "r": 0.8556753396987915,
                "f1": 0.8425987362861633
            },
            "rouge-l": {
                "p": 0.22048063423035522,
                "r": 0.19129604582546,
                "f1": 0.19763611439505577
            }
        },
        "ro-en-----./wmt2b_ckpts/ro-envanilla256100___finally": {
            "bleu": {
                "1": 0.25736820257368204,
                "2": 0.15186462690815566,
                "3": 0.09603958077031845,
                "4": 0.0599779710544102
            },
            "bertscore": {
                "p": 0.8221158385276794,
                "r": 0.869402289390564,
                "f1": 0.8443513512611389
            },
            "rouge-l": {
                "p": 0.27802608163770215,
                "r": 0.24501424026550647,
                "f1": 0.24766069107402516
            }
        },
        "ro-en-----./wmt2b_ckpts/ro-enkd256100___finally": {
            "bleu": {
                "1": 0.0037823072073965135,
                "2": 0.0018020300987601548,
                "3": 0.0011243744621190878,
                "4": 0.0007502296298025289
            },
            "bertscore": {
                "p": 0.6209499835968018,
                "r": 0.813112199306488,
                "f1": 0.7035892009735107
            },
            "rouge-l": {
                "p": 0.03251190476190476,
                "r": 0.011111219597632642,
                "f1": 0.014783829343161277
            }
        },
        "ro-en-----./wmt2b_ckpts/ro-enblack--Complex-lord256100___period2": {
            "bleu": {
                "1": 0.21092029942756496,
                "2": 0.10973372494767636,
                "3": 0.06037675719472778,
                "4": 0.03463650641281599
            },
            "bertscore": {
                "p": 0.8312614560127258,
                "r": 0.8539560437202454,
                "f1": 0.8418058753013611
            },
            "rouge-l": {
                "p": 0.23704432678249635,
                "r": 0.20113970488376354,
                "f1": 0.20657730540187125
            }
        }
    },
    "ru-en": {
        "ru-en-----./wmt2b_ckpts/ru-enComplex-lord256100___period2": {
            "bleu": {
                "1": 0.06290379475197727,
                "2": 0.028931530195715878,
                "3": 0.015246239196456023,
                "4": 0.007994760493065056
            },
            "bertscore": {
                "p": 0.7602918744087219,
                "r": 0.7997646927833557,
                "f1": 0.7778846621513367
            },
            "rouge-l": {
                "p": 0.14177696846762494,
                "r": 0.08659838831783885,
                "f1": 0.10084812116714385
            }
        },
        "ru-en-----./wmt2b_ckpts/ru-envanilla256100___finally": {
            "bleu": {
                "1": 0.1682764591004471,
                "2": 0.1041271997237367,
                "3": 0.0680814457756239,
                "4": 0.04727817680387843
            },
            "bertscore": {
                "p": 0.8066598773002625,
                "r": 0.8430148363113403,
                "f1": 0.8231735229492188
            },
            "rouge-l": {
                "p": 0.23337191889404565,
                "r": 0.14397243995096828,
                "f1": 0.17068061693271455
            }
        },
        "ru-en-----./wmt2b_ckpts/ru-enkd256100___finally": {
            "bleu": {
                "1": 0.0,
                "2": 0.0,
                "3": 0.0,
                "4": 0.0
            },
            "bertscore": {
                "p": 0.6604560613632202,
                "r": 0.8074766397476196,
                "f1": 0.7263455390930176
            },
            "rouge-l": {
                "p": 0.0,
                "r": 0.0,
                "f1": 0.0
            }
        },
        "ru-en-----./wmt2b_ckpts/ru-enblack--Complex-lord256100___period2": {
            "bleu": {
                "1": 0.08646478817877228,
                "2": 0.03556791962150372,
                "3": 0.018027514420941103,
                "4": 0.008500458869388727
            },
            "bertscore": {
                "p": 0.8035886883735657,
                "r": 0.8075481653213501,
                "f1": 0.8052060008049011
            },
            "rouge-l": {
                "p": 0.1285561611022485,
                "r": 0.08540324484274917,
                "f1": 0.09306531755011123
            }
        }
    },
    "tr-en": {
        "tr-en-----./wmt2b_ckpts/tr-enComplex-lord256100___period2": {
            "bleu": {
                "1": 0.15764331210191085,
                "2": 0.05780154259840735,
                "3": 0.021410645893990964,
                "4": 0.010501563020567796
            },
            "bertscore": {
                "p": 0.7582387328147888,
                "r": 0.7645647525787354,
                "f1": 0.7608928680419922
            },
            "rouge-l": {
                "p": 0.1613188196687881,
                "r": 0.14059947992749205,
                "f1": 0.1380520954611743
            }
        },
        "tr-en-----./wmt2b_ckpts/tr-envanilla256100___finally": {
            "bleu": {
                "1": 0.09341688194885661,
                "2": 0.044220227296668045,
                "3": 0.02380796381909669,
                "4": 0.014519930917078748
            },
            "bertscore": {
                "p": 0.7386940121650696,
                "r": 0.7825378179550171,
                "f1": 0.7585128545761108
            },
            "rouge-l": {
                "p": 0.1102083047356267,
                "r": 0.07457235922790034,
                "f1": 0.0841740974057185
            }
        },
        "tr-en-----./wmt2b_ckpts/tr-enkd256100___finally": {
            "bleu": {
                "1": 0.01101228293096146,
                "2": 0.004934843694457306,
                "3": 0.0,
                "4": 0.0
            },
            "bertscore": {
                "p": 0.6498371958732605,
                "r": 0.8077090382575989,
                "f1": 0.7193663120269775
            },
            "rouge-l": {
                "p": 0.05635714285714286,
                "r": 0.01567372211122211,
                "f1": 0.023165152986141174
            }
        },
        "tr-en-----./wmt2b_ckpts/tr-enblack--Complex-lord256100___period2": {
            "bleu": {
                "1": 0.1962339875174196,
                "2": 0.08197914984172072,
                "3": 0.036184504258568256,
                "4": 0.017671464697669937
            },
            "bertscore": {
                "p": 0.8333852291107178,
                "r": 0.8448053002357483,
                "f1": 0.8383146524429321
            },
            "rouge-l": {
                "p": 0.17915179052387958,
                "r": 0.14755696985796038,
                "f1": 0.15723978862033752
            }
        }
    }
}